README.txt
setup.cfg
setup.py
docs/HISTORY.txt
docs/INSTALL.txt
docs/LICENSE.GPL
docs/LICENSE.txt
quills/__init__.py
quills.core.egg-info/PKG-INFO
quills.core.egg-info/SOURCES.txt
quills.core.egg-info/dependency_links.txt
quills.core.egg-info/entry_points.txt
quills.core.egg-info/namespace_packages.txt
quills.core.egg-info/not-zip-safe
quills.core.egg-info/requires.txt
quills.core.egg-info/top_level.txt
quills/core/__init__.py
quills/core/configure.zcml
quills/core/rebuild_i18n.sh
quills/core/version.txt
quills/core/browser/__init__.py
quills/core/browser/interfaces.py
quills/core/browser/weblogconfig.py
quills/core/interfaces/__init__.py
quills/core/interfaces/archive.py
quills/core/interfaces/basecontent.py
quills/core/interfaces/enabled.py
quills/core/interfaces/topic.py
quills/core/interfaces/weblog.py
quills/core/interfaces/weblogentry.py
quills/core/locales/quills.core-manual.pot
quills/core/locales/quills.core.pot
quills/core/locales/cy/LC_MESSAGES/quills.core.po
quills/core/locales/da/LC_MESSAGES/quills.core.po
quills/core/locales/de/LC_MESSAGES/quills.core.po
quills/core/locales/en/LC_MESSAGES/quills.core.po
quills/core/locales/es/LC_MESSAGES/quills.core.po
quills/core/locales/eu/LC_MESSAGES/quills.core.po
quills/core/locales/fr/LC_MESSAGES/quills.core.po
quills/core/locales/it/LC_MESSAGES/quills.core.po
quills/core/locales/ja/LC_MESSAGES/quills.core.po
quills/core/locales/lt/LC_MESSAGES/quills.core.po
quills/core/locales/nl/LC_MESSAGES/quills.core.po
quills/core/locales/pt-br/LC_MESSAGES/quills.core.po
quills/core/locales/pt/LC_MESSAGES/quills.core.po
quills/core/locales/ru/LC_MESSAGES/quills.core.po
quills/core/locales/sr-Latn/LC_MESSAGES/quills.core.po
quills/core/locales/sr/LC_MESSAGES/quills.core.po
quills/core/tests/__init__.py
quills/core/tests/test_doctests.py
quills/core/tests/tests.txt