Metadata-Version: 1.0
Name: quills.core
Version: 1.7.0
Summary: Core weblog interfaces and views for Quills.
Home-page: http://plone.org/products/quills
Author: Quills Team
Author-email: plone-quills@googlegroups.com
License: GPL
Download-URL: http://svn.plone.org/svn/collective/quills.core
Keywords: plone blogging
Platform: UNKNOWN
Classifier: Development Status :: 5 - Production/Stable
Classifier: Framework :: Plone
Classifier: License :: OSI Approved :: GNU General Public License (GPL)
Classifier: Programming Language :: Python
Classifier: Topic :: Software Development :: Libraries :: Python Modules
